modfy/ProcessServer.py
modfy/__init__.py
modfy/auth.py
modfy/config.py
modfy/main.py
modfy-0.0.1.dist-info/LICENSE
modfy-0.0.1.dist-info/METADATA
modfy-0.0.1.dist-info/WHEEL
modfy-0.0.1.dist-info/top_level.txt
modfy-0.0.1.dist-info/RECORD
